__init__.py
dataprocessor/__init__.py
dataprocessor/constants.py
dataprocessor/data_processor.py
dataprocessor/feed_filter.py
dataprocessor/utils.py
example/example.py
dataprocessor-0.0.20.dist-info/LICENSE
dataprocessor-0.0.20.dist-info/METADATA
dataprocessor-0.0.20.dist-info/WHEEL
dataprocessor-0.0.20.dist-info/top_level.txt
dataprocessor-0.0.20.dist-info/RECORD
