Metadata-Version: 2.1
Name: dataprocessor
Version: 0.0.20
Summary: DataProcessor extends the piping abilities for pandas DataFrame with a DateTimeIndex by wrapping it in a DataProcessor class
Author-email: hraoyama <hraoyama@gmail.com>
Project-URL: Homepage, https://github.com/hraoyama/dataprocessor
Project-URL: Issues, https://github.com/hraoyama/dataprocessor/issues
Classifier: Programming Language :: Python :: 3
Classifier: License :: OSI Approved :: MIT License
Classifier: Operating System :: OS Independent
Requires-Python: >=3.9
License-File: LICENSE
Requires-Dist: faker >=20.0
